{"instance":{"Decoration/Group/Default":[{"i":0,"x":20,"y":23,"z":0,"data":{"width":1057,"height":301,"title":"Example without custom keyring","color":""}},{"i":1,"x":19,"y":335,"z":1,"data":{"width":1055,"height":353,"title":"Example with custom keyring that using sr25519","color":""}}],"Console/Log":[{"i":2,"x":872,"y":161,"z":2,"comment":"Address on ChainId: 42"},{"i":3,"x":850,"y":470,"z":3},{"i":4,"x":609,"y":51,"z":4}],"Polkadot.js/Convert/Address To/Address":[{"i":5,"x":567,"y":573,"z":5,"input_d":{"Address":"","ChainId":0}},{"i":6,"x":610,"y":174,"z":6,"output":{"Address":[{"i":2,"name":"Any"}]}}],"Decoration/Text/Notes":[{"i":7,"x":42,"y":582,"z":7,"data":{"value":"tide spot unfold innocent soup crawl danger know resource time staff knife"}}],"Input/UI/SliderBox":[{"i":8,"x":367,"y":213,"z":8,"data":{"0":{"value":42,"min":-100,"max":100,"step":0.1,"hideUnusedPort":false}},"output":{"0":[{"i":6,"name":"ChainId"}]}},{"i":9,"x":366,"y":611,"z":9,"data":{"0":{"value":42,"min":-100,"max":100,"step":0.1}}}],"Input/UI/TextBox":[{"i":10,"x":39,"y":124,"z":10,"comment":"Input your test wallet's mnemonic here","data":{"value":""},"output":{"Value":[{"i":13,"name":"Mnemonic"}]}},{"i":11,"x":42,"y":483,"z":11,"comment":"Input your another test wallet's mnemonic here","data":{"value":""},"output":{"Value":[{"i":14,"name":"Mnemonic"}]}},{"i":12,"x":327,"y":371,"z":12,"data":{"value":"sr25519"},"output":{"Value":[{"i":15,"name":"KeyType"}]}}],"Polkadot.js/Keyring/Create/Keypair":[{"i":13,"x":312,"y":108,"z":13,"output":{"Address":[{"i":4,"name":"Any","parentId":0},{"i":6,"name":"Address","parentId":1}]},"_cable":{"Address":[{"x":566,"y":175,"branch":[{"id":0},{"id":1}]}]}},{"i":14,"x":576,"y":452,"z":16,"comment":"Use our custom keyring","output":{"Address":[{"i":3,"name":"Any"}]}}],"Polkadot.js/Keyring/Create/Keyring":[{"i":15,"x":327,"y":452,"z":14,"output":{"Keyring":[{"i":14,"name":"Keyring"}]}}],"Polkadot.js/Keyring/Create/Mnemonic":[{"i":16,"x":43,"y":236,"z":15}]},"moduleJS":["https://cdn.jsdelivr.net/npm/@blackprint/nodes@0.7.x/dist/nodes-decoration.mjs","https://cdn.jsdelivr.net/npm/@blackprint/nodes@0.7.x/dist/nodes-console.mjs","https://cdn.jsdelivr.net/npm/@blackprint/nodes-polkadot.js@0.6.x/dist/nodes-polkadotjs.mjs","https://cdn.jsdelivr.net/npm/@blackprint/nodes@0.7.x/dist/nodes-input.mjs"]}